odoo/addons/delivery_slip_packages/README.rst
odoo/addons/delivery_slip_packages/__init__.py
odoo/addons/delivery_slip_packages/__manifest__.py
odoo/addons/delivery_slip_packages/i18n/ca_ES.po
odoo/addons/delivery_slip_packages/i18n/es.po
odoo/addons/delivery_slip_packages/models/__init__.py
odoo/addons/delivery_slip_packages/models/stock_picking_type.py
odoo/addons/delivery_slip_packages/readme/CONTRIBUTORS.md
odoo/addons/delivery_slip_packages/readme/DESCRIPTION.md
odoo/addons/delivery_slip_packages/readme/USAGE.md
odoo/addons/delivery_slip_packages/static/description/icon.png
odoo/addons/delivery_slip_packages/static/description/index.html
odoo/addons/delivery_slip_packages/views/report_delivery_slip_with_packages.xml
odoo/addons/delivery_slip_packages/views/stock_picking_type_view.xml
odoo_addon_delivery_slip_packages-17.0.1.0.0.1.dist-info/METADATA
odoo_addon_delivery_slip_packages-17.0.1.0.0.1.dist-info/WHEEL
odoo_addon_delivery_slip_packages-17.0.1.0.0.1.dist-info/top_level.txt
odoo_addon_delivery_slip_packages-17.0.1.0.0.1.dist-info/RECORD
